README.md
setup.py
ipfslib/__init__.py
ipfslib/connect.py
ipfslib/IPFS/__init__.py
ipfslib/IPFS/add.py
ipfslib/IPFS/cat.py
ipfslib/IPFS/get.py
ipfslib/IPFS/rem.py
ipfslib/IPFS/resolve.py
ipfslib/Key/__init__.py
ipfslib/Key/generate.py
ipfslib/Key/list.py
ipfslib/Key/publish.py
ipfslib/Key/rename.py
ipfslib_fix.egg-info/PKG-INFO
ipfslib_fix.egg-info/SOURCES.txt
ipfslib_fix.egg-info/dependency_links.txt
ipfslib_fix.egg-info/top_level.txt