Metadata-Version: 2.1
Name: ipfslib-fix
Version: 0.1.1
Summary: IPFS Library for Python Fix
Author: Christian Remboldt
Author-email: society@csec.eu.org
Keywords: python,ipfs,api,decentral,networking,ipns
Classifier: Programming Language :: Python :: 3
